marinholab/working/needlemanipulation/__init__.py
marinholab/working/needlemanipulation/_core.cp311-win_amd64.pyd
marinholab/working/needlemanipulation/_impl.py
marinholab/working/needlemanipulation/example.py
marinholab/working/needlemanipulation/example_create_needle_controller.py
marinholab/working/needlemanipulation/example_kinematics_from_coppeliasim.py
marinholab/working/needlemanipulation/example_load_from_file.py
marinholab/working/needlemanipulation/icra2019_controller.py
marinholab/working/needlemanipulation/left_robot.yaml
marinholab/working/needlemanipulation/needle_controller.py
marinholab/working/needlemanipulation/right_robot.yaml
marinholab_working_needlemanipulation-25.6.0.68.dist-info/LICENSE
marinholab_working_needlemanipulation-25.6.0.68.dist-info/METADATA
marinholab_working_needlemanipulation-25.6.0.68.dist-info/WHEEL
marinholab_working_needlemanipulation-25.6.0.68.dist-info/entry_points.txt
marinholab_working_needlemanipulation-25.6.0.68.dist-info/top_level.txt
marinholab_working_needlemanipulation-25.6.0.68.dist-info/RECORD
