Metadata-Version: 2.1
Name: marinholab-working-needlemanipulation
Version: 25.6.0.68
Summary: Ongoing work on needle manipulation in a collaboration between UTokyo and UoM.
Author-email: "Murilo M. Marinho" <murilomarinho@ieee.org>
Maintainer-email: "Murilo M. Marinho" <murilomarinho@ieee.org>
License: MIT
Requires-Python: >=3.9
License-File: LICENSE
Requires-Dist: dqrobotics>=23.4.0a49
Requires-Dist: quadprog
Requires-Dist: termcolor
Requires-Dist: pyyaml
